LICENSE
MANIFEST.in
README.md
README.rst
requirements.txt
setup.cfg
setup.py
versioneer.py
pyccc/__init__.py
pyccc/_native.py
pyccc/_version.py
pyccc/backports.py
pyccc/docker_utils.py
pyccc/exceptions.py
pyccc/job.py
pyccc/picklers.py
pyccc/python.py
pyccc/source_inspections.py
pyccc/status.py
pyccc/ui.py
pyccc/utils.py
pyccc.egg-info/PKG-INFO
pyccc.egg-info/SOURCES.txt
pyccc.egg-info/dependency_links.txt
pyccc.egg-info/requires.txt
pyccc.egg-info/top_level.txt
pyccc/engines/__init__.py
pyccc/engines/base.py
pyccc/engines/dockerengine.py
pyccc/engines/subproc.py
pyccc/files/__init__.py
pyccc/files/base.py
pyccc/files/bytecontainer.py
pyccc/files/directory.py
pyccc/files/localfiles.py
pyccc/files/remotefiles.py
pyccc/files/stringcontainer.py
pyccc/static/run_job.py
pyccc/tests/__init__.py
pyccc/tests/engine_fixtures.py
pyccc/tests/function_tests.py
pyccc/tests/requirements.txt
pyccc/tests/test_dir_refs.py
pyccc/tests/test_engine_specific_features.py
pyccc/tests/test_engines.py
pyccc/tests/test_file_refs.py
pyccc/tests/data/a
pyccc/tests/data/b