Metadata-Version: 1.1
Name: pyccc
Version: 0.10.3
Summary: Asynchronous job and file i/o management for containers)
Home-page: http://github.com/autodesk/pyccc
Author: Aaron Virshup and Dion Amago, Autodesk Life Sciences
Author-email: moleculardesigntoolkit@autodesk.com
License: Apache 2.0
Platform: UNKNOWN
Classifier: Development Status :: 4 - Beta
Classifier: Natural Language :: English
Classifier: Intended Audience :: Science/Research
Classifier: Intended Audience :: Developers
Classifier: License :: OSI Approved :: Apache Software License
Classifier: Programming Language :: Python :: 2
Classifier: Programming Language :: Python :: 2.7
Classifier: Programming Language :: Python :: 3
Classifier: Programming Language :: Python :: 3.5
Classifier: Programming Language :: Python :: 3.6
Classifier: Topic :: System :: Distributed Computing
Classifier: Operating System :: POSIX
Classifier: Operating System :: Unix
Classifier: Operating System :: MacOS
